[{"model": "store.artist", "pk": 2, "fields": {"name": "Serge Beynaud"}}, {"model": "store.artist", "pk": 3, "fields": {"name": "Arafat DJ"}}, {"model": "store.artist", "pk": 4, "fields": {"name": "BB Philip"}}, {"model": "store.artist", "pk": 5, "fields": {"name": "Mix DJ"}}, {"model": "store.artist", "pk": 6, "fields": {"name": "Kerozen DJ"}}, {"model": "store.artist", "pk": 7, "fields": {"name": "Constance"}}, {"model": "store.artist", "pk": 8, "fields": {"name": "Genevieve Brou"}}, {"model": "store.artist", "pk": 9, "fields": {"name": "Francis Cabrel"}}, {"model": "store.artist", "pk": 10, "fields": {"name": "Yoloanda Adams"}}, {"model": "store.artist", "pk": 11, "fields": {"name": "Stephane Query"}}, {"model": "store.contact", "pk": 1, "fields": {"email": "ewac@gmail.com", "name": "Abbe"}}, {"model": "store.contact", "pk": 8, "fields": {"email": "jac@gmail.com", "name": "Jack"}}, {"model": "store.album", "pk": 1, "fields": {"reference": 1, "created_at": "2019-10-07T19:07:00.682Z", "available": false, "title": "Accelerate", "picture": "http://wp.sergebeynaud.com/wp-content/uploads/2017/05/Accelerate-300x300.jpg", "artists": [2]}}, {"model": "store.album", "pk": 2, "fields": {"reference": 0, "created_at": "2019-10-07T19:23:13.675Z", "available": false, "title": "akrakabo", "picture": "https://encrypted-tbn0.gstatic.com/images?q=tbn%3AANd9GcS_FpTtD1px7vIiIva61dAULS6PFIFVNvADrN74Qdk_Uk4pPFN0", "artists": []}}, {"model": "store.album", "pk": 3, "fields": {"reference": 2, "created_at": "2019-10-07T19:26:26.821Z", "available": false, "title": "Louez Yaveh", "picture": "https://i.ytimg.com/vi/2HCxXunXwEg/maxresdefault.jpg", "artists": [8, 10]}}, {"model": "store.album", "pk": 4, "fields": {"reference": 1, "created_at": "2019-10-07T19:29:27.304Z", "available": true, "title": "Sarbacane", "picture": "https://www.olies-darts.com/8097-thickbox_default/sarbacane-full-kit-violet-040-inch-105-mm.jpg", "artists": [9]}}, {"model": "store.album", "pk": 5, "fields": {"reference": 0, "created_at": "2019-10-07T19:31:12.934Z", "available": false, "title": "I believe in God", "picture": "https://www.bestsayingsquotes.com/files/god-quotes-pictures-for-profile-6-dbc31f5d.jpg", "artists": [7, 8, 10]}}, {"model": "store.album", "pk": 6, "fields": {"reference": 1, "created_at": "2019-10-12T03:44:55.605Z", "available": true, "title": "Je puis tout", "picture": "https://s.mxmcdn.net/images-storage/albums/1/9/6/9/2/1/27129691_800_800.jpg", "artists": [7]}}, {"model": "store.album", "pk": 7, "fields": {"reference": 1, "created_at": "2019-10-12T03:46:20.216Z", "available": true, "title": "Je donne gloire", "picture": "https://www.clcfrance.com/couvertures/LALCD2925.jpg", "artists": [11]}}, {"model": "store.booking", "pk": 1, "fields": {"created_at": "2019-10-09T15:24:31.922Z", "contacted": false, "album": 5, "contact": 1}}, {"model": "store.booking", "pk": 2, "fields": {"created_at": "2019-10-11T05:13:23.526Z", "contacted": false, "album": 3, "contact": 8}}, {"model": "store.booking", "pk": 3, "fields": {"created_at": "2019-10-11T05:19:59.197Z", "contacted": false, "album": 2, "contact": 8}}, {"model": "store.booking", "pk": 4, "fields": {"created_at": "2019-10-11T05:21:45.552Z", "contacted": false, "album": 1, "contact": 8}}]